tdsbconnects/__init__.py
tdsbconnects/objects.py
tdsbconnects/tdsbconnects.py
tdsbconnects/util.py
tdsbconnects/version.py
pytdsbconnects-0.1.1.dist-info/LICENSE
pytdsbconnects-0.1.1.dist-info/METADATA
pytdsbconnects-0.1.1.dist-info/WHEEL
pytdsbconnects-0.1.1.dist-info/top_level.txt
pytdsbconnects-0.1.1.dist-info/RECORD
